constify/__init__.py
constify/_freezeparams.py
constify/py.typed
constify-0.1.0.dist-info/LICENSE
constify-0.1.0.dist-info/METADATA
constify-0.1.0.dist-info/WHEEL
constify-0.1.0.dist-info/top_level.txt
constify-0.1.0.dist-info/RECORD
