Metadata-Version: 2.2
Name: constify
Version: 0.1.0
Summary: Makes functions parameters immutable
Author-email: YARO Ali <ali.yaro@hotmail.com>
License: MIT
Project-URL: Repository, https://github.com/yazernin10x/constify
Project-URL: Issue tracker, https://github.com/yazernin10x/constify/issues
Keywords: mutable,immutable,decorator,default values,mutable arguments
Classifier: Development Status :: 5 - Production/Stable
Classifier: Intended Audience :: Developers
Classifier: License :: OSI Approved :: MIT License
Classifier: Operating System :: OS Independent
Classifier: Programming Language :: Python
Classifier: Programming Language :: Python :: 3
Classifier: Programming Language :: Python :: 3.9
Classifier: Programming Language :: Python :: 3.10
Classifier: Programming Language :: Python :: 3.11
Classifier: Programming Language :: Python :: 3.12
Classifier: Programming Language :: Python :: 3.13
Requires-Python: >=3.9
License-File: LICENSE
Provides-Extra: dev
Requires-Dist: ruff; extra == "dev"
Requires-Dist: mypy; extra == "dev"
Provides-Extra: test
Requires-Dist: tox; extra == "test"
Requires-Dist: coverage; extra == "test"
